LICENSE
MANIFEST.in
README.md
setup.cfg
setup.py
sqlalchemy_mogdb/__init__.py
sqlalchemy_mogdb/array.py
sqlalchemy_mogdb/asyncpg.py
sqlalchemy_mogdb/base.py
sqlalchemy_mogdb/dialect.py
sqlalchemy_mogdb/dml.py
sqlalchemy_mogdb/ext.py
sqlalchemy_mogdb/hstore.py
sqlalchemy_mogdb/json.py
sqlalchemy_mogdb/provision.py
sqlalchemy_mogdb/psycopg2.py
sqlalchemy_mogdb/psycopg2cffi.py
sqlalchemy_mogdb/ranges.py
sqlalchemy_mogdb.egg-info/PKG-INFO
sqlalchemy_mogdb.egg-info/SOURCES.txt
sqlalchemy_mogdb.egg-info/dependency_links.txt
sqlalchemy_mogdb.egg-info/entry_points.txt
sqlalchemy_mogdb.egg-info/requires.txt
sqlalchemy_mogdb.egg-info/top_level.txt