Metadata-Version: 2.1
Name: sqlalchemy-mogdb
Version: 0.1.2
Summary: Enmotech MogDB Dialect for SQLAlchemy
Home-page: https://gitee.com/enmotech/sqlalchemy-mogdb
Author: Enmotech
Maintainer: Vimiix
Maintainer-email: i@vimiix.com
License: MIT
Keywords: Enmotech MogDB
Classifier: Development Status :: 4 - Beta
Classifier: Environment :: Console
Classifier: Intended Audience :: Developers
Classifier: License :: OSI Approved :: MIT License
Classifier: Operating System :: OS Independent
Classifier: Programming Language :: Python
Classifier: Programming Language :: Python :: 2
Classifier: Programming Language :: Python :: 2.7
Classifier: Programming Language :: Python :: 3
Classifier: Programming Language :: Python :: 3.6
Classifier: Programming Language :: Python :: 3.7
Classifier: Programming Language :: Python :: 3.8
Classifier: Programming Language :: Python :: 3.9
License-File: LICENSE
